charlib/__init__.py
charlib/characterizer/Characterizer.py
charlib/characterizer/Harness.py
charlib/characterizer/LogicParser.py
charlib/characterizer/README.md
charlib/characterizer/TestManager.py
charlib/characterizer/__init__.py
charlib/characterizer/functions/__init__.py
charlib/characterizer/functions/functions.py
charlib/characterizer/functions/functions.yml
charlib/characterizer/run.py
charlib/liberty/README.md
charlib/liberty/UnitsSettings.py
charlib/liberty/__init__.py
charlib/liberty/cell.py
charlib/liberty/library.py
charlib-1.0.0.dist-info/LICENSE
charlib-1.0.0.dist-info/METADATA
charlib-1.0.0.dist-info/WHEEL
charlib-1.0.0.dist-info/entry_points.txt
charlib-1.0.0.dist-info/RECORD
