Metadata-Version: 2.1
Name: charlib
Version: 1.0.0
Summary: An open-source standard cell library characterizer
Home-page: https://github.com/stineje/CharLib
License: GPL-2.0
Author: Marcus Mellor
Author-email: infinitymdm@gmail.com
Requires-Python: >=3.9,<4.0
Classifier: License :: OSI Approved :: GNU General Public License v2 (GPLv2)
Classifier: Programming Language :: Python :: 3
Classifier: Programming Language :: Python :: 3.9
Classifier: Programming Language :: Python :: 3.10
Classifier: Programming Language :: Python :: 3.11
Classifier: Programming Language :: Python :: 3.12
Requires-Dist: liberty-parser (>=0.0.16,<0.0.17)
Requires-Dist: matplotlib (>=3.8.2,<4.0.0)
Requires-Dist: numpy (>=1.26.2,<2.0.0)
Requires-Dist: pyyaml (>=6.0.1,<7.0.0)
Project-URL: Repository, https://github.com/stineje/CharLib
